design.sv
module alu #(
  parameter int W = 32
)(
  input  logic [W-1:0] a,
  input  logic [W-1:0] b,
  input  logic [3:0]   op,
  output logic [W-1:0] y,
  output logic         zero
);

  // op encoding
  localparam logic [3:0]
    OP_ADD = 4'h0,
    OP_SUB = 4'h1,
    OP_AND = 4'h2,
    OP_OR  = 4'h3,
    OP_XOR = 4'h4,
    OP_SLT = 4'h5,
    OP_SLL = 4'h6,
    OP_SRL = 4'h7;

  logic signed [W-1:0] as, bs;

  always_comb begin
    as = a;
    bs = b;
    unique case (op)
      OP_ADD: y = a + b;
      OP_SUB: y = a - b;
      OP_AND: y = a & b;
      OP_OR : y = a | b;
      OP_XOR: y = a ^ b;
      OP_SLT: y = (as < bs) ? {{(W-1){1'b0}}, 1'b1} : '0;
      OP_SLL: y = a << b[$clog2(W)-1:0];
      OP_SRL: y = a >> b[$clog2(W)-1:0];
      default: y = '0;
    endcase
  end

  always_comb begin
    zero = (y == '0);
  end

endmodule

testbench.sv
module tb_alu;

  localparam int W = 32;

  logic [W-1:0] a, b;
  logic [3:0]   op;
  logic [W-1:0] y;
  logic         zero;

  alu #(.W(W)) dut (
    .a(a), .b(b), .op(op),
    .y(y), .zero(zero)
  );

  function automatic logic [W-1:0] golden(
    input logic [W-1:0] a_g,
    input logic [W-1:0] b_g,
    input logic [3:0]   op_g
  );
    logic signed [W-1:0] as, bs;
    as = a_g; bs = b_g;

    unique case (op_g)
      4'h0: golden = a_g + b_g;
      4'h1: golden = a_g - b_g;
      4'h2: golden = a_g & b_g;
      4'h3: golden = a_g | b_g;
      4'h4: golden = a_g ^ b_g;
      4'h5: golden = (as < bs) ? {{(W-1){1'b0}},1'b1} : '0;
      4'h6: golden = a_g << b_g[$clog2(W)-1:0];
      4'h7: golden = a_g >> b_g[$clog2(W)-1:0];
      default: golden = '0;
    endcase
  endfunction

  int errors = 0;

  task automatic run_one(input int idx);
    logic [W-1:0] exp;
    exp = golden(a,b,op);
    #1;
    if (y !== exp) begin
      errors++;
      $display("[FAIL] i=%0d op=%0h a=%0h b=%0h | y=%0h exp=%0h",
               idx, op, a, b, y, exp);
    end
    if (zero !== (exp=='0)) begin
      errors++;
      $display("[FAIL-Z] i=%0d op=%0h a=%0h b=%0h | zero=%0b exp_zero=%0b",
               idx, op, a, b, zero, (exp=='0));
    end
  endtask

  initial begin
    a = 32'd10; b = 32'd5; op = 4'h0; run_one(-1); // add
    op = 4'h1; run_one(-2); // sub
    op = 4'h2; run_one(-3); // and
    op = 4'h5; run_one(-4); // slt

    
    for (int i = 0; i < 1000; i++) begin
      a  = $urandom();
      b  = $urandom();
      op = $urandom_range(0,7);
      run_one(i);
    end

    if (errors == 0) $display("\n ALL TESTS PASSED\n");
    else            $display("\n TESTS FAILED: %0d errors\n", errors);

    $finish;
  end
  initial begin
    $dumpfile("dump.vcd");
    $dumpvars;
  end

endmodule

dump.vcd
$date
Fri Jan  2 19:21:13 2026
$end
$version
Riviera-PRO Version 2023.04.112.8911
$end
$timescale
1 ns
$end

$scope module tb_alu $end
$var reg 32 ! a [31:0] $end
$var reg 32 " b [31:0] $end
$var reg 4 # op [3:0] $end
$var reg 32 $ y [31:0] $end
$var reg 1 % zero $end
$var integer 32 & errors $end
$var parameter 32 ' W [31:0] $end

$scope module dut $end
$var wire 32 ( a [31:0] $end
$var wire 32 ) b [31:0] $end
$var wire 4 * op [3:0] $end
$var reg 32 + y [31:0] $end
$var reg 1 , zero $end
$var reg 32 - as [31:0] $end
$var reg 32 . bs [31:0] $end
$var parameter 32 / W [31:0] $end
$var parameter 4 0 OP_ADD [3:0] $end
$var parameter 4 1 OP_SUB [3:0] $end
$var parameter 4 2 OP_AND [3:0] $end
$var parameter 4 3 OP_OR [3:0] $end
$var parameter 4 4 OP_XOR [3:0] $end
$var parameter 4 5 OP_SLT [3:0] $end
$var parameter 4 6 OP_SLL [3:0] $end
$var parameter 4 7 OP_SRL [3:0] $end
$upscope $end


$scope function golden $end
$upscope $end


$scope task run_one $end
$upscope $end

$upscope $end

$enddefinitions $end
$dumpvars
b1010 !
b101 "
b0 #
b1111 $
0%
b0 &
b100000 '
b1010 (
b101 )
b0 *
b1111 +
0,
b1010 -
b101 .
b100000 /
b0 0
b1 1
b10 2
b11 3
b100 4
b101 5
b110 6
b111 7
$end
#1
b1 #
b1 *
b101 +
b101 $
#2
b10 #
b10 *
b0 +
b0 $
1,
1%
#3
b101 #
b101 *
#4
b11001000000001101101110000100010 !
b10001101000111111110110011001110 "
b11 #
b11 *
b10001101000111111110110011001110 )
b11001000000001101101110000100010 (
b11001000000001101101110000100010 -
b10001101000111111110110011001110 .
b11001101000111111111110011101110 +
b11001101000111111111110011101110 $
0,
0%
#5
b10110000000000001111110111000100 !
b11111011001101000100011001101001 "
b0 #
b0 *
b11111011001101000100011001101001 )
b10110000000000001111110111000100 (
b10110000000000001111110111000100 -
b11111011001101000100011001101001 .
b10101011001101010100010000101101 +
b10101011001101010100010000101101 $
#6
b10111010111111011000010111001011 !
b10010111111011011010101100100110 "
b110 #
b110 *
b10010111111011011010101100100110 )
b10111010111111011000010111001011 (
b10111010111111011000010111001011 -
b10010111111011011010101100100110 .
b10111111011000010111001011000000 +
b10111111011000010111001011000000 $
#7
b101111010110111111100000110000 !
b11111010110101110111101000111110 "
b11111010110101110111101000111110 )
b101111010110111111100000110000 (
b101111010110111111100000110000 -
b11111010110101110111101000111110 .
b0 +
b0 $
1,
1%
#8
b11101100110110011010101010001110 !
b10011000111100100110110001100000 "
b0 #
b0 *
b10011000111100100110110001100000 )
b11101100110110011010101010001110 (
b11101100110110011010101010001110 -
b10011000111100100110110001100000 .
b10000101110011000001011011101110 +
b10000101110011000001011011101110 $
0,
0%
#9
b10011110100100100001010101100001 !
b11000101110000111100110110111 "
b101 #
b101 *
b11000101110000111100110110111 )
b10011110100100100001010101100001 (
b10011110100100100001010101100001 -
b11000101110000111100110110111 .
b1 +
b1 $
#10
b100110011100000100010000100011 !
b1001000001100111001001111101101 "
b111 #
b111 *
b1001000001100111001001111101101 )
b100110011100000100010000100011 (
b100110011100000100010000100011 -
b1001000001100111001001111101101 .
b10011001110000010 +
b10011001110000010 $
#11
b11001000101110101100000101100101 !
b1001101011100001000001011010001 "
b100 #
b100 *
b1001101011100001000001011010001 )
b11001000101110101100000101100101 (
b11001000101110101100000101100101 -
b1001101011100001000001011010001 .
b10000101110010100100001110110100 +
b10000101110010100100001110110100 $
#12
b1010110010110011111000001101 !
b11111101111000100101100110001111 "
b11 #
b11 *
b11111101111000100101100110001111 )
b1010110010110011111000001101 (
b1010110010110011111000001101 -
b11111101111000100101100110001111 .
b11111111111010110111111110001111 +
b11111111111010110111111110001111 $
#13
b1100101101110000101101001110010 !
b1110011110101101001111011010101 "
b100 #
b100 *
b1110011110101101001111011010101 )
b1100101101110000101101001110010 (
b1100101101110000101101001110010 -
b1110011110101101001111011010101 .
b10110011011101100010010100111 +
b10110011011101100010010100111 $
#14
b1011010101000010100101101001001 !
b11110000110011111000100001010100 "
b110 #
b110 *
b11110000110011111000100001010100 )
b1011010101000010100101101001001 (
b1011010101000010100101101001001 -
b11110000110011111000100001010100 .
b10110100100100000000000000000000 +
b10110100100100000000000000000000 $
#15
b110100111110101110101001101000 !
b1011001110011101100111000100011 "
b10 #
b10 *
b1011001110011101100111000100011 )
b110100111110101110101001101000 (
b110100111110101110101001101000 -
b1011001110011101100111000100011 .
b10000110010101100101000100000 +
b10000110010101100101000100000 $
#16
b1111001111010001110110110101111 !
b11001001010111110011100011110110 "
b0 #
b0 *
b11001001010111110011100011110110 )
b1111001111010001110110110101111 (
b1111001111010001110110110101111 -
b11001001010111110011100011110110 .
b1000011010010000010011010100101 +
b1000011010010000010011010100101 $
#17
b100001111100111011111100000110 !
b10110011110110001010010010010010 "
b100 #
b100 *
b10110011110110001010010010010010 )
b100001111100111011111100000110 (
b100001111100111011111100000110 -
b10110011110110001010010010010010 .
b10010010001010110001101110010100 +
b10010010001010110001101110010100 $
#18
b11001001001101100010100100101110 !
b10010110100001010001001111111110 "
b0 #
b0 *
b10010110100001010001001111111110 )
b11001001001101100010100100101110 (
b11001001001101100010100100101110 -
b10010110100001010001001111111110 .
b1011111101110110011110100101100 +
b1011111101110110011110100101100 $
#19
b1001001101101011001001110101010 !
b11100010011100110101100111101010 "
b111 #
b111 *
b11100010011100110101100111101010 )
b1001001101101011001001110101010 (
b1001001101101011001001110101010 -
b11100010011100110101100111101010 .
b100100110110101100100 +
b100100110110101100100 $
#20
b11111000000011100100110000110110 !
b1100110000010100000011000000010 "
b1 #
b1 *
b1100110000010100000011000000010 )
b11111000000011100100110000110110 (
b11111000000011100100110000110110 -
b1100110000010100000011000000010 .
b10010010000001000100011000110100 +
b10010010000001000100011000110100 $
#21
b1111011100010100010011111101011 !
b100000011100001111010101100110 "
b11 #
b11 *
b100000011100001111010101100110 )
b1111011100010100010011111101011 (
b1111011100010100010011111101011 -
b100000011100001111010101100110 .
b1111011111110101111011111101111 +
b1111011111110101111011111101111 $
#22
b10111011001110111010101111011110 !
b11110101011010111011110011001110 "
b10 #
b10 *
b11110101011010111011110011001110 )
b10111011001110111010101111011110 (
b10111011001110111010101111011110 -
b11110101011010111011110011001110 .
b10110001001010111010100011001110 +
b10110001001010111010100011001110 $
#23
b1011010110101000000010001110111 !
b11001001100110101100010001000110 "
b11 #
b11 *
b11001001100110101100010001000110 )
b1011010110101000000010001110111 (
b1011010110101000000010001110111 -
b11001001100110101100010001000110 .
b11011011110111101100010001110111 +
b11011011110111101100010001110111 $
#24
b10010101010001111111110110110101 !
b1000001100001000100111001011110 "
b1 #
b1 *
b1000001100001000100111001011110 )
b10010101010001111111110110110101 (
b10010101010001111111110110110101 -
b1000001100001000100111001011110 .
b1010011110000111010111101010111 +
b1010011110000111010111101010111 $
#25
b11111000000010111110001111110100 !
b111100010111111000101011001011 "
b11 #
b11 *
b111100010111111000101011001011 )
b11111000000010111110001111110100 (
b11111000000010111110001111110100 -
b111100010111111000101011001011 .
b11111100010111111110101111111111 +
b11111100010111111110101111111111 $
#26
b100100000111000110101000111001 !
b11101000000100000010001011110011 "
b10 #
b10 *
b11101000000100000010001011110011 )
b100100000111000110101000111001 (
b100100000111000110101000111001 -
b11101000000100000010001011110011 .
b100000000100000010001000110001 +
b100000000100000010001000110001 $
#27
b1000110111001100100011111011110 !
b1110100101010100010010001000000 "
b11 #
b11 *
b1110100101010100010010001000000 )
b1000110111001100100011111011110 (
b1000110111001100100011111011110 -
b1110100101010100010010001000000 .
b1110110111011100110011111011110 +
b1110110111011100110011111011110 $
#28
b11010011011010101101001101001 !
b1101110111111000011000110100001 "
b110 #
b110 *
b1101110111111000011000110100001 )
b11010011011010101101001101001 (
b11010011011010101101001101001 -
b1101110111111000011000110100001 .
b110100110110101011010011010010 +
b110100110110101011010011010010 $
#29
b11101110001111000100000110001011 !
b11011010111001010110000111011001 "
b0 #
b0 *
b11011010111001010110000111011001 )
b11101110001111000100000110001011 (
b11101110001111000100000110001011 -
b11011010111001010110000111011001 .
b11001001001000011010001101100100 +
b11001001001000011010001101100100 $
#30
b1011011000010011010111111110001 !
b10110001011101001110001100110100 "
b10 #
b10 *
b10110001011101001110001100110100 )
b1011011000010011010111111110001 (
b1011011000010011010111111110001 -
b10110001011101001110001100110100 .
b10001000000001010001100110000 +
b10001000000001010001100110000 $
#31
b100110110101101111010111100011 !
b10111111000010010011100110001001 "
b1 #
b1 *
b10111111000010010011100110001001 )
b100110110101101111010111100011 (
b100110110101101111010111100011 -
b10111111000010010011100110001001 .
b1100111110011011011110001011010 +
b1100111110011011011110001011010 $
#32
b1000000111110110101101011011000 !
b10001010101000001000100110111 "
b11 #
b11 *
b10001010101000001000100110111 )
b1000000111110110101101011011000 (
b1000000111110110101101011011000 -
b10001010101000001000100110111 .
b1010001111111110101101111111111 +
b1010001111111110101101111111111 $
#33
b10000101101101111110111001110111 !
b10101011101111001000110100100110 "
b101 #
b101 *
b10101011101111001000110100100110 )
b10000101101101111110111001110111 (
b10000101101101111110111001110111 -
b10101011101111001000110100100110 .
b1 +
b1 $
#34
b10010110111011010110100011000100 !
b11111111101110111010011101111110 "
b1 #
b1 *
b11111111101110111010011101111110 )
b10010110111011010110100011000100 (
b10010110111011010110100011000100 -
b11111111101110111010011101111110 .
b10010111001100011100000101000110 +
b10010111001100011100000101000110 $
#35
b10100100011010000111010011101001 !
b1001101110011100100111101110001 "
b111 #
b111 *
b1001101110011100100111101110001 )
b10100100011010000111010011101001 (
b10100100011010000111010011101001 -
b1001101110011100100111101110001 .
b101001000110100 +
b101001000110100 $
#36
b1001111100101000100100101000 !
b111010010101111110010001101 "
b101 #
b101 *
b111010010101111110010001101 )
b1001111100101000100100101000 (
b1001111100101000100100101000 -
b111010010101111110010001101 .
b0 +
b0 $
1,
1%
#37
b1101000010000110000110111101111 !
b10011100001101100101111111011100 "
b111 #
b111 *
b10011100001101100101111111011100 )
b1101000010000110000110111101111 (
b1101000010000110000110111101111 -
b10011100001101100101111111011100 .
b110 +
b110 $
0,
0%
#38
b11001011111110001110011011111010 !
b1010100100110001000110101011 "
b11 #
b11 *
b1010100100110001000110101011 )
b11001011111110001110011011111010 (
b11001011111110001110011011111010 -
b1010100100110001000110101011 .
b11001011111110111111011111111011 +
b11001011111110111111011111111011 $
#39
b111100111101100011111101011010 !
b11001100010110111100100101 "
b101 #
b101 *
b11001100010110111100100101 )
b111100111101100011111101011010 (
b111100111101100011111101011010 -
b11001100010110111100100101 .
b0 +
b0 $
1,
1%
#40
b10011110100011001111001111000010 !
b101111010010010110000001 "
b100 #
b100 *
b101111010010010110000001 )
b10011110100011001111001111000010 (
b10011110100011001111001111000010 -
b101111010010010110000001 .
b10011110001100011101011001000011 +
b10011110001100011101011001000011 $
0,
0%
#41
b10010110010001010011000011011111 !
b1111111001010000110111000011011 "
b10 #
b10 *
b1111111001010000110111000011011 )
b10010110010001010011000011011111 (
b10010110010001010011000011011111 -
b1111111001010000110111000011011 .
b10110000000000010000000011011 +
b10110000000000010000000011011 $
#42
b10100000010111011010000100100010 !
b10110001101001100110110010010101 "
b11 #
b11 *
b10110001101001100110110010010101 )
b10100000010111011010000100100010 (
b10100000010111011010000100100010 -
b10110001101001100110110010010101 .
b10110001111111111110110110110111 +
b10110001111111111110110110110111 $
#43
b11101110101011101111100110011000 !
b11001101100010011011110100101101 "
b1 #
b1 *
b11001101100010011011110100101101 )
b11101110101011101111100110011000 (
b11101110101011101111100110011000 -
b11001101100010011011110100101101 .
b100001001001010011110001101011 +
b100001001001010011110001101011 $
#44
b1011010010100000101110100101000 !
b110001100011110100100001001 "
b110 #
b110 *
b110001100011110100100001001 )
b1011010010100000101110100101000 (
b1011010010100000101110100101000 -
b110001100011110100100001001 .
b10100000101110100101000000000000 +
b10100000101110100101000000000000 $
#45
b10111100111000011001110001111001 !
b11110101101101000101111010010001 "
b11 #
b11 *
b11110101101101000101111010010001 )
b10111100111000011001110001111001 (
b10111100111000011001110001111001 -
b11110101101101000101111010010001 .
b11111101111101011101111011111001 +
b11111101111101011101111011111001 $
#46
b11111110111100100100001100001001 !
b1101010011110000100111101011100 "
b111 #
b111 *
b1101010011110000100111101011100 )
b11111110111100100100001100001001 (
b11111110111100100100001100001001 -
b1101010011110000100111101011100 .
b1111 +
b1111 $
#47
b11111110001000100110010000101001 !
b10110100111000010001111000100101 "
b110 #
b110 *
b10110100111000010001111000100101 )
b11111110001000100110010000101001 (
b11111110001000100110010000101001 -
b10110100111000010001111000100101 .
b11000100010011001000010100100000 +
b11000100010011001000010100100000 $
#48
b10111100011000010010100010011 !
b1010111101101110011100000100011 "
b111 #
b111 *
b1010111101101110011100000100011 )
b10111100011000010010100010011 (
b10111100011000010010100010011 -
b1010111101101110011100000100011 .
b10111100011000010010100010 +
b10111100011000010010100010 $
#49
b1111000100011101000101100000000 !
b1010001111101011100100101011000 "
b101 #
b101 *
b1010001111101011100100101011000 )
b1111000100011101000101100000000 (
b1111000100011101000101100000000 -
b1010001111101011100100101011000 .
b0 +
b0 $
1,
1%
#50
b11101101101111010110111111011 !
b11000100100010011001111011110100 "
b11 #
b11 *
b11000100100010011001111011110100 )
b11101101101111010110111111011 (
b11101101101111010110111111011 -
b11000100100010011001111011110100 .
b11011101101111111011111111111111 +
b11011101101111111011111111111111 $
0,
0%
#51
b10110100110100000111011000011110 !
b10010011001011110111111010111100 "
b0 #
b0 *
b10010011001011110111111010111100 )
b10110100110100000111011000011110 (
b10110100110100000111011000011110 -
b10010011001011110111111010111100 .
b1000111111111111111010011011010 +
b1000111111111111111010011011010 $
#52
b111110111110011010011011010001 !
b11101101110000000110110011111100 "
b100 #
b100 *
b11101101110000000110110011111100 )
b111110111110011010011011010001 (
b111110111110011010011011010001 -
b11101101110000000110110011111100 .
b11010011001110011100101000101101 +
b11010011001110011100101000101101 $
#53
b11000101010011100101001011010001 !
b11111011111001010000000010000 "
b111 #
b111 *
b11111011111001010000000010000 )
b11000101010011100101001011010001 (
b11000101010011100101001011010001 -
b11111011111001010000000010000 .
b1100010101001110 +
b1100010101001110 $
#54
b11111010100111101100010000111110 !
b1011100101100101001100111110010 "
b1 #
b1 *
b1011100101100101001100111110010 )
b11111010100111101100010000111110 (
b11111010100111101100010000111110 -
b1011100101100101001100111110010 .
b10011101111011000010101001001100 +
b10011101111011000010101001001100 $
#55
b10000111101001010010101111000101 !
b1100001010100000101101011101010 "
b110 #
b110 *
b1100001010100000101101011101010 )
b10000111101001010010101111000101 (
b10000111101001010010101111000101 -
b1100001010100000101101011101010 .
b10010100101011110001010000000000 +
b10010100101011110001010000000000 $
#56
b11010110001110010000100011011101 !
b1110010101000001101100001100100 "
b1 #
b1 *
b1110010101000001101100001100100 )
b11010110001110010000100011011101 (
b11010110001110010000100011011101 -
b1110010101000001101100001100100 .
b1100011100110000011000001111001 +
b1100011100110000011000001111001 $
#57
b10011111110011001111110110011 !
b10011101011100011101101100111110 "
b101 #
b101 *
b10011101011100011101101100111110 )
b10011111110011001111110110011 (
b10011111110011001111110110011 -
b10011101011100011101101100111110 .
b0 +
b0 $
1,
1%
#58
b10010101110110010001101111001011 !
b11111111011000111101101010011000 "
b0 #
b0 *
b11111111011000111101101010011000 )
b10010101110110010001101111001011 (
b10010101110110010001101111001011 -
b11111111011000111101101010011000 .
b10010101001111001111011001100011 +
b10010101001111001111011001100011 $
0,
0%
#59
b11100010001101101101010110001111 !
b100101000000100110000001110110 "
b1 #
b1 *
b100101000000100110000001110110 )
b11100010001101101101010110001111 (
b11100010001101101101010110001111 -
b100101000000100110000001110110 .
b10111101001101000111010100011001 +
b10111101001101000111010100011001 $
#60
b111000100000111011100111000000 !
b100101100010001001001101110010 "
b100101100010001001001101110010 )
b111000100000111011100111000000 (
b111000100000111011100111000000 -
b100101100010001001001101110010 .
b10010111110110010011001001110 +
b10010111110110010011001001110 $
#61
b11010100101000100010101001100000 !
b11111000100101110110100011100100 "
b110 #
b110 *
b11111000100101110110100011100100 )
b11010100101000100010101001100000 (
b11010100101000100010101001100000 -
b11111000100101110110100011100100 .
b1001010001000101010011000000000 +
b1001010001000101010011000000000 $
#62
b11100101101000111111010001001111 !
b11011011000010111101100011111 "
b11 #
b11 *
b11011011000010111101100011111 )
b11100101101000111111010001001111 (
b11100101101000111111010001001111 -
b11011011000010111101100011111 .
b11111111111000111111111101011111 +
b11111111111000111111111101011111 $
#63
b10010001011100101111001101000100 !
b11011101111110100100100010101000 "
b100 #
b100 *
b11011101111110100100100010101000 )
b10010001011100101111001101000100 (
b10010001011100101111001101000100 -
b11011101111110100100100010101000 .
b1001100100010001011101111101100 +
b1001100100010001011101111101100 $
#64
b11100110011010010001011000100111 !
b110100111001000110000101110100 "
b101 #
b101 *
b110100111001000110000101110100 )
b11100110011010010001011000100111 (
b11100110011010010001011000100111 -
b110100111001000110000101110100 .
b1 +
b1 $
#65
b11101111001110011001101001010100 !
b10101001010000111001100001100001 "
b110 #
b110 *
b10101001010000111001100001100001 )
b11101111001110011001101001010100 (
b11101111001110011001101001010100 -
b10101001010000111001100001100001 .
b11011110011100110011010010101000 +
b11011110011100110011010010101000 $
#66
b1010111000111100000110001100010 !
b1010101101100101100100001000100 "
b101 #
b101 *
b1010101101100101100100001000100 )
b1010111000111100000110001100010 (
b1010111000111100000110001100010 -
b1010101101100101100100001000100 .
b0 +
b0 $
1,
1%
#67
b110010011001111110011101100101 !
b11111000100001110100010101001010 "
b100 #
b100 *
b11111000100001110100010101001010 )
b110010011001111110011101100101 (
b110010011001111110011101100101 -
b11111000100001110100010101001010 .
b11001010111000001010001000101111 +
b11001010111000001010001000101111 $
0,
0%
#68
b110000000001111010001000110 !
b11111101111001111010111000011010 "
b110 #
b110 *
b11111101111001111010111000011010 )
b110000000001111010001000110 (
b110000000001111010001000110 -
b11111101111001111010111000011010 .
b11000000000000000000000000000 +
b11000000000000000000000000000 $
#69
b1110111100110000111110111010101 !
b1110000010000110111111110001011 "
b1110000010000110111111110001011 )
b1110111100110000111110111010101 (
b1110111100110000111110111010101 -
b1110000010000110111111110001011 .
b11000011111011101010100000000000 +
b11000011111011101010100000000000 $
#70
b11111001100101100011001000000111 !
b1001010001101010010111000010101 "
b10 #
b10 *
b1001010001101010010111000010101 )
b11111001100101100011001000000111 (
b11111001100101100011001000000111 -
b1001010001101010010111000010101 .
b1001000000101000010001000000101 +
b1001000000101000010001000000101 $
#71
b101000010010000000111011100010 !
b11001110101110001001110011100101 "
b11001110101110001001110011100101 )
b101000010010000000111011100010 (
b101000010010000000111011100010 -
b11001110101110001001110011100101 .
b1000000010000000110011100000 +
b1000000010000000110011100000 $
#72
b10011001111100110001000001101101 !
b10001110000110011111001111100010 "
b111 #
b111 *
b10001110000110011111001111100010 )
b10011001111100110001000001101101 (
b10011001111100110001000001101101 -
b10001110000110011111001111100010 .
b100110011111001100010000011011 +
b100110011111001100010000011011 $
#73
b10101110111111011000010001000100 !
b11101110011101110001010100001011 "
b0 #
b0 *
b11101110011101110001010100001011 )
b10101110111111011000010001000100 (
b10101110111111011000010001000100 -
b11101110011101110001010100001011 .
b10011101011101001001100101001111 +
b10011101011101001001100101001111 $
#74
b1011001000110011010101001100101 !
b110100110000010100101011111110 "
b110100110000010100101011111110 )
b1011001000110011010101001100101 (
b1011001000110011010101001100101 -
b110100110000010100101011111110 .
b10001101110110101111010101100011 +
b10001101110110101111010101100011 $
#75
b11110111010000100011111110 !
b111100101000010101001000111010 "
b110 #
b110 *
b111100101000010101001000111010 )
b11110111010000100011111110 (
b11110111010000100011111110 -
b111100101000010101001000111010 .
b11111000000000000000000000000000 +
b11111000000000000000000000000000 $
#76
b11110100010000011001011011101000 !
b1011010001111110001011011000111 "
b1011010001111110001011011000111 )
b11110100010000011001011011101000 (
b11110100010000011001011011101000 -
b1011010001111110001011011000111 .
b100000110010110111010000000000 +
b100000110010110111010000000000 $
#77
b1101011001010110011010100011 !
b1100011001111001111101111111000 "
b1100011001111001111101111111000 )
b1101011001010110011010100011 (
b1101011001010110011010100011 -
b1100011001111001111101111111000 .
b10100011000000000000000000000000 +
b10100011000000000000000000000000 $
#78
b11011001000111101100110011000011 !
b111011010111010101010100001111 "
b111 #
b111 *
b111011010111010101010100001111 )
b11011001000111101100110011000011 (
b11011001000111101100110011000011 -
b111011010111010101010100001111 .
b11011001000111101 +
b11011001000111101 $
#79
b1010110101010000011101101111111 !
b10111100011111111111001011111111 "
b110 #
b110 *
b10111100011111111111001011111111 )
b1010110101010000011101101111111 (
b1010110101010000011101101111111 -
b10111100011111111111001011111111 .
b10000000000000000000000000000000 +
b10000000000000000000000000000000 $
#80
b10000111001100000100011100011100 !
b10000000000111000111111100100101 "
b11 #
b11 *
b10000000000111000111111100100101 )
b10000111001100000100011100011100 (
b10000111001100000100011100011100 -
b10000000000111000111111100100101 .
b10000111001111000111111100111101 +
b10000111001111000111111100111101 $
#81
b11110110111100000010101001100110 !
b1011110101000110011110010111000 "
b101 #
b101 *
b1011110101000110011110010111000 )
b11110110111100000010101001100110 (
b11110110111100000010101001100110 -
b1011110101000110011110010111000 .
b1 +
b1 $
#82
b10110100001110010110110011001001 !
b1011100110100000011110110010000 "
b1011100110100000011110110010000 )
b10110100001110010110110011001001 (
b10110100001110010110110011001001 -
b1011100110100000011110110010000 .
#83
b10001000111111101111100011010 !
b1111011011101011110100111011100 "
b111 #
b111 *
b1111011011101011110100111011100 )
b10001000111111101111100011010 (
b10001000111111101111100011010 -
b1111011011101011110100111011100 .
#84
b1111100001010001110101111011111 !
b110101100110000000011110000 "
b11 #
b11 *
b110101100110000000011110000 )
b1111100001010001110101111011111 (
b1111100001010001110101111011111 -
b110101100110000000011110000 .
b1111110101110111110101111111111 +
b1111110101110111110101111111111 $
#85
b11110111001010001010101001111110 !
b11000011010110011100010011 "
b101 #
b101 *
b11000011010110011100010011 )
b11110111001010001010101001111110 (
b11110111001010001010101001111110 -
b11000011010110011100010011 .
b1 +
b1 $
#86
b11100001000100111110111111110110 !
b1110010011010011111011001000 "
b110 #
b110 *
b1110010011010011111011001000 )
b11100001000100111110111111110110 (
b11100001000100111110111111110110 -
b1110010011010011111011001000 .
b10011111011111111011000000000 +
b10011111011111111011000000000 $
#87
b1111110000101100010000000011101 !
b1010010010110101110111110100101 "
b10 #
b10 *
b1010010010110101110111110100101 )
b1111110000101100010000000011101 (
b1111110000101100010000000011101 -
b1010010010110101110111110100101 .
b1010010000100100010000000000101 +
b1010010000100100010000000000101 $
#88
b10101011011000010010010100011000 !
b1100110110001111101101100010110 "
b101 #
b101 *
b1100110110001111101101100010110 )
b10101011011000010010010100011000 (
b10101011011000010010010100011000 -
b1100110110001111101101100010110 .
b1 +
b1 $
#89
b11010011101011111001001010100100 !
b100111110101111101100110011000 "
b100111110101111101100110011000 )
b11010011101011111001001010100100 (
b11010011101011111001001010100100 -
b100111110101111101100110011000 .
#90
b11010101100010010101001011101 !
b1110001000111111100000000001001 "
b10 #
b10 *
b1110001000111111100000000001001 )
b11010101100010010101001011101 (
b11010101100010010101001011101 -
b1110001000111111100000000001001 .
b10000000100010000000000001001 +
b10000000100010000000000001001 $
#91
b11110001101000100001111101011111 !
b10111010101100111011111011001 "
b11 #
b11 *
b10111010101100111011111011001 )
b11110001101000100001111101011111 (
b11110001101000100001111101011111 -
b10111010101100111011111011001 .
b11110111111101100111111111011111 +
b11110111111101100111111111011111 $
#92
b11110000100001001011111010011000 !
b1111100010001010101101100110010 "
b101 #
b101 *
b1111100010001010101101100110010 )
b11110000100001001011111010011000 (
b11110000100001001011111010011000 -
b1111100010001010101101100110010 .
b1 +
b1 $
#93
b10100011110000110011100011100011 !
b1100000101100110010101000110101 "
b1100000101100110010101000110101 )
b10100011110000110011100011100011 (
b10100011110000110011100011100011 -
b1100000101100110010101000110101 .
#94
b1100001100000000101111010100100 !
b11000100011110111011110000000000 "
b0 #
b0 *
b11000100011110111011110000000000 )
b1100001100000000101111010100100 (
b1100001100000000101111010100100 -
b11000100011110111011110000000000 .
b100101111111000001101010100100 +
b100101111111000001101010100100 $
#95
b1101000000110001101111101100101 !
b10111111100000100011010001011010 "
b110 #
b110 *
b10111111100000100011010001011010 )
b1101000000110001101111101100101 (
b1101000000110001101111101100101 -
b10111111100000100011010001011010 .
b10010100000000000000000000000000 +
b10010100000000000000000000000000 $
#96
b11100110000000110001000000110111 !
b10101100010101011111000101110010 "
b0 #
b0 *
b10101100010101011111000101110010 )
b11100110000000110001000000110111 (
b11100110000000110001000000110111 -
b10101100010101011111000101110010 .
b10010010010110010000000110101001 +
b10010010010110010000000110101001 $
#97
b11101000101000100000000101101001 !
b10101101010000011110110000010010 "
b11 #
b11 *
b10101101010000011110110000010010 )
b11101000101000100000000101101001 (
b11101000101000100000000101101001 -
b10101101010000011110110000010010 .
b11101101111000111110110101111011 +
b11101101111000111110110101111011 $
#98
b1111010011011111110100111111 !
b10000010000111110001010100111011 "
b10000010000111110001010100111011 )
b1111010011011111110100111111 (
b1111010011011111110100111111 -
b10000010000111110001010100111011 .
b10001111010111111111110100111111 +
b10001111010111111111110100111111 $
#99
b10110110000001100110100111010110 !
b11001011001011100000110001101111 "
b11001011001011100000110001101111 )
b10110110000001100110100111010110 (
b10110110000001100110100111010110 -
b11001011001011100000110001101111 .
b11111111001011100110110111111111 +
b11111111001011100110110111111111 $
#100
b11000011000101010010001100110011 !
b101100011000101100000011001011 "
b0 #
b0 *
b101100011000101100000011001011 )
b11000011000101010010001100110011 (
b11000011000101010010001100110011 -
b101100011000101100000011001011 .
b11101111011101111110001111111110 +
b11101111011101111110001111111110 $
#101
b10011110000101010011100010010000 !
b10101111001011100100111010101111 "
b10 #
b10 *
b10101111001011100100111010101111 )
b10011110000101010011100010010000 (
b10011110000101010011100010010000 -
b10101111001011100100111010101111 .
b10001110000001000000100010000000 +
b10001110000001000000100010000000 $
#102
b111000110110001111111011101001 !
b1100100001001000010011111100 "
b1100100001001000010011111100 )
b111000110110001111111011101001 (
b111000110110001111111011101001 -
b1100100001001000010011111100 .
b1000100000001000010011101000 +
b1000100000001000010011101000 $
#103
b11110100111001011011100100100001 !
b1011110101011110010001011111000 "
b100 #
b100 *
b1011110101011110010001011111000 )
b11110100111001011011100100100001 (
b11110100111001011011100100100001 -
b1011110101011110010001011111000 .
b10101010010010101001101111011001 +
b10101010010010101001101111011001 $
#104
b100101011001011001100011000101 !
b10010111100100001111011101011011 "
b1 #
b1 *
b10010111100100001111011101011011 )
b100101011001011001100011000101 (
b100101011001011001100011000101 -
b10010111100100001111011101011011 .
b10001101110101001010000101101010 +
b10001101110101001010000101101010 $
